dem2basin/__init__.py
dem2basin/dem2basin.py
dem2basin-0.9.0.1.dist-info/LICENSE
dem2basin-0.9.0.1.dist-info/METADATA
dem2basin-0.9.0.1.dist-info/WHEEL
dem2basin-0.9.0.1.dist-info/top_level.txt
dem2basin-0.9.0.1.dist-info/RECORD
