Metadata-Version: 2.1
Name: dem2basin
Version: 0.9.0.1
Summary: Tools to derive HUC-cropped DEMs from common DEM datasets
Home-page: https://github.com/dhardestylewis/DEM2basin
Author: Daniel Hardesty Lewis
Author-email: dhl@tacc.utexas.edu
License: GPL-3.0-or-later
Project-URL: Code, https://github.com/dhardestylewis/DEM2basin
Project-URL: Bug Tracker, https://github.com/dhardestylewis/DEM2basin/issues
Project-URL: Issues, https://github.com/dhardestylewis/DEM2basin/issues
Platform: UNKNOWN
Classifier: Programming Language :: Python :: 3
Classifier: Intended Audience :: Science/Research
Classifier: License :: OSI Approved :: GNU General Public License v3 or later (GPLv3+)
Classifier: Operating System :: OS Independent
Classifier: Topic :: Scientific/Engineering
Classifier: Topic :: Scientific/Engineering :: GIS
Requires-Python: >=3.6
License-File: LICENSE
Requires-Dist: utm
Requires-Dist: tblib
Requires-Dist: descartes
Requires-Dist: fiona
Requires-Dist: numpy
Requires-Dist: matplotlib
Requires-Dist: scipy
Requires-Dist: geopandas
Requires-Dist: pandas
Requires-Dist: rasterio
Requires-Dist: pyproj
Requires-Dist: contextily
Requires-Dist: xlrd
Requires-Dist: openpyxl
Requires-Dist: rio-tiler
Requires-Dist: terracotta
Requires-Dist: memory-profiler
Requires-Dist: psutil
Requires-Dist: rtree
